README.md
setup.py
Chromoy.egg-info/PKG-INFO
Chromoy.egg-info/SOURCES.txt
Chromoy.egg-info/dependency_links.txt
Chromoy.egg-info/requires.txt
Chromoy.egg-info/top_level.txt
chromoy/__init__.py
chromoy/base.py
chromoy/exceptions.py
chromoy/settings.py