Metadata-Version: 1.0
Name: Chromoy
Version: 0.6
Summary: Refreshed chrome-driver for parsing and cron-testing.
Home-page: https://github.com/Beastrock/Chromoy
Author: Alexey Savchenko
Author-email: beastrock@mail.ru
License: UNKNOWN
Platform: UNKNOWN
